{
  "state": [
    {
      "key": "snake_x",
      "description": "Snake head X position in pixels",
      "js_expression": "snake.x",
      "type": "number"
    },
    {
      "key": "snake_y",
      "description": "Snake head Y position in pixels",
      "js_expression": "snake.y",
      "type": "number"
    },
    {
      "key": "snake_velocity_x",
      "description": "Snake X velocity in pixels per frame",
      "js_expression": "snake.dx",
      "type": "number"
    },
    {
      "key": "snake_velocity_y",
      "description": "Snake Y velocity in pixels per frame",
      "js_expression": "snake.dy",
      "type": "number"
    },
    {
      "key": "snake_current_length",
      "description": "Current number of cells in the snake's body",
      "js_expression": "snake.cells.length",
      "type": "number"
    },
    {
      "key": "snake_target_length",
      "description": "The length the snake will attempt to maintain, increases when eating apples",
      "js_expression": "snake.maxCells",
      "type": "number"
    },
    {
      "key": "apple_x",
      "description": "Regular apple X position in pixels",
      "js_expression": "apple.x",
      "type": "number"
    },
    {
      "key": "apple_y",
      "description": "Regular apple Y position in pixels",
      "js_expression": "apple.y",
      "type": "number"
    },
    {
      "key": "bonus_apples_on_screen",
      "description": "Number of bonus apples currently spawned on the screen",
      "js_expression": "bonusApples.length",
      "type": "number"
    },
    {
      "key": "wall_obstacles_on_screen",
      "description": "Number of wall obstacle segments (groups of 3) currently on the screen",
      "js_expression": "walls.length",
      "type": "number"
    },
    {
      "key": "is_speed_burst_active",
      "description": "True if a speed burst is currently active",
      "js_expression": "window.__snakeSpeedBurst > 0 && window.__snakeSpeedBurstTimer > 0",
      "type": "boolean"
    },
    {
      "key": "speed_burst_timer_frames",
      "description": "Remaining frames for the current speed burst",
      "js_expression": "window.__snakeSpeedBurstTimer",
      "type": "number"
    },
    {
      "key": "effective_frame_skip",
      "description": "The actual number of frames skipped between game updates, affecting game speed.",
      "js_expression": "var baseSkip = window.__snakeFrameSkip != null ? window.__snakeFrameSkip : 3; (window.__snakeSpeedBurst > 0 && window.__snakeSpeedBurstTimer > 0) ? Math.max(1, baseSkip - window.__snakeSpeedBurst) : baseSkip",
      "type": "number"
    }
  ],
  "mods": [
    {
      "key": "game_frame_skip",
      "label": "Game Frame Skip",
      "description": "Number of frames to skip before updating game state. Higher value means slower game.",
      "js_get": "window.__snakeFrameSkip != null ? window.__snakeFrameSkip : 3",
      "js_set": "window.__snakeFrameSkip = VALUE",
      "default": 3,
      "min": 1,
      "max": 10,
      "step": 1,
      "category": "speed"
    },
    {
      "key": "bonus_apple_count",
      "label": "Bonus Apple Count",
      "description": "Number of extra bonus apples maintained on screen.",
      "js_get": "window.__snakeBonusCount || 0",
      "js_set": "window.__snakeBonusCount = VALUE",
      "default": 0,
      "min": 0,
      "max": 10,
      "step": 1,
      "category": "reward"
    },
    {
      "key": "wall_obstacle_count",
      "label": "Wall Obstacle Count",
      "description": "Number of wall segments (groups of 3) maintained on screen.",
      "js_get": "window.__snakeWallCount || 0",
      "js_set": "window.__snakeWallCount = VALUE",
      "default": 0,
      "min": 0,
      "max": 5,
      "step": 1,
      "category": "obstacle"
    },
    {
      "key": "apple_growth_points",
      "label": "Apple Growth Points",
      "description": "Number of cells the snake grows when eating a regular apple.",
      "js_get": "window.__appleGrowthPoints || 1",
      "js_set": "window.__appleGrowthPoints = VALUE",
      "default": 1,
      "min": 1,
      "max": 5,
      "step": 1,
      "category": "reward"
    },
    {
      "key": "snake_initial_length",
      "label": "Snake Initial Length",
      "description": "The starting length of the snake when the game begins or resets.",
      "js_get": "window.__snakeInitialLength || 4",
      "js_set": "window.__snakeInitialLength = VALUE; snake.maxCells = VALUE;",
      "default": 4,
      "min": 1,
      "max": 10,
      "step": 1,
      "category": "difficulty"
    },
    {
      "key": "grid_cell_size",
      "label": "Grid Cell Size",
      "description": "The size of each grid cell in pixels. Affects visual scale and movement unit.",
      "js_get": "grid",
      "js_set": "grid = VALUE",
      "default": 16,
      "min": 8,
      "max": 32,
      "step": 1,
      "category": "visual"
    },
    {
      "key": "speed_burst_amount",
      "label": "Speed Burst Amount",
      "description": "Extra frame skip reduction applied during a speed burst (higher value means faster burst).",
      "js_get": "window.__snakeSpeedBurst || 0",
      "js_set": "window.__snakeSpeedBurst = VALUE",
      "default": 0,
      "min": 0,
      "max": 3,
      "step": 1,
      "category": "speed"
    },
    {
      "key": "speed_burst_duration",
      "label": "Speed Burst Duration",
      "description": "Number of frames a speed burst lasts when activated.",
      "js_get": "window.__snakeSpeedBurstTimer || 0",
      "js_set": "window.__snakeSpeedBurstTimer = VALUE",
      "default": 0,
      "min": 0,
      "max": 300,
      "step": 10,
      "category": "speed"
    }
  ],
  "engagement_mod_keys": [
    "game_frame_skip",
    "bonus_apple_count",
    "wall_obstacle_count",
    "apple_growth_points",
    "snake_initial_length",
    "speed_burst_amount",
    "speed_burst_duration"
  ]
}